Metadata-Version: 1.1
Name: coordstring
Version: 0.2.0
Summary: Fast collection for geospatial coordinates
Home-page: https://github.com/fortyninemaps/coordstring
Author: Nat Wilson
Author-email: natw@fortyninemaps.com
License: MIT License
Platform: UNKNOWN
Classifier: Programming Language :: Python :: 2
Classifier: Programming Language :: Python :: 2.7
Classifier: Programming Language :: Python :: 3
Classifier: Programming Language :: Python :: 3.4
Classifier: Programming Language :: Python :: 3.5
Classifier: Programming Language :: Python :: 3.6
Classifier: Topic :: Scientific/Engineering
Classifier: Topic :: Scientific/Engineering :: GIS
Classifier: License :: OSI Approved :: MIT License
